LICENSE
MANIFEST.in
README.rst
conf.py
icu_bidi.rst
index.rst
setup.cfg
setup.py
PyICU_BiDi.egg-info/PKG-INFO
PyICU_BiDi.egg-info/SOURCES.txt
PyICU_BiDi.egg-info/dependency_links.txt
PyICU_BiDi.egg-info/requires.txt
PyICU_BiDi.egg-info/top_level.txt
icu_bidi/__init__.py
icu_bidi/_impl.py
icu_bidi/test_impl.py